[ {
	"duration": 1,
	"sprite": "Bonnie\\291.png"
}, {
	"duration": 1,
	"sprite": "Bonnie\\293.png"
}, {
	"duration": 1,
	"sprite": "Bonnie\\294.png"
}, {
	"duration": 1,
	"sprite": "Bonnie\\295.png"
}, {
	"duration": 1,
	"sprite": "Bonnie\\296.png"
}, {
	"duration": 1,
	"sprite": "Bonnie\\297.png"
}, {
	"duration": 1,
	"sprite": "Bonnie\\298.png"
}, {
	"duration": 1,
	"sprite": "Bonnie\\299.png"
}, {
	"duration": 1,
	"sprite": "Bonnie\\300.png"
}, {
	"duration": 1,
	"sprite": "Bonnie\\301.png"
}, {
	"duration": 1,
	"sprite": "Bonnie\\303.png"
} ]